src/BradleyChess/Agent.py
src/BradleyChess/Bradley.py
src/BradleyChess/Environ.py
src/BradleyChess/Settings.py
src/BradleyChess/__init__.py
src/BradleyChess/helper_methods.py
src/BradleyChess/main.py
bradleychess_rl_chess_engine-0.0.1.dist-info/METADATA
bradleychess_rl_chess_engine-0.0.1.dist-info/WHEEL
bradleychess_rl_chess_engine-0.0.1.dist-info/licenses/LICENSE.txt
bradleychess_rl_chess_engine-0.0.1.dist-info/RECORD
